.graphics.old/src/int_vga.v
module int_vga (
    input wire clk,           // Clock input (25 MHz)
    input wire reset,         // Reset input
    output wire hsync,        // Horizontal sync output
    output wire vsync,        // Vertical sync output
    output reg [3:0] red,     // Red color output
    output reg [3:0] green,   // Green color output
    output reg [3:0] blue,    // Blue color output
    input wire [3:0] in_red,  // External red input
    input wire [3:0] in_green,// External green input
    input wire [3:0] in_blue  // External blue input
);

    // VGA 240p (NTSC-like) resolution timing parameters
    parameter H_DISPLAY = 320;  // Active horizontal pixels
    parameter H_FRONT = 8;      // Horizontal front porch
    parameter H_SYNC = 48;      // Horizontal sync pulse width
    parameter H_BACK = 24;      // Horizontal back porch
    parameter V_DISPLAY = 240;  // Active vertical pixels
    parameter V_FRONT = 2;      // Vertical front porch
    parameter V_SYNC = 2;       // Vertical sync pulse width
    parameter V_BACK = 15;      // Vertical back porch

    // Total screen size including blanking
    parameter H_TOTAL = H_DISPLAY + H_FRONT + H_SYNC + H_BACK;  // 400 pixels
    parameter V_TOTAL = V_DISPLAY + V_FRONT + V_SYNC + V_BACK;  // 259 lines

    // Counters
    reg [9:0] h_count = 0;
    reg [9:0] v_count = 0;

    // Horizontal sync generation
    always @(posedge clk or posedge reset) begin
        if (reset)
            h_count <= 0;
        else if (h_count == H_TOTAL - 1)
            h_count <= 0;
        else
            h_count <= h_count + 1;
    end

    // Vertical sync generation
    always @(posedge clk or posedge reset) begin
        if (reset)
            v_count <= 0;
        else if (h_count == H_TOTAL - 1) begin
            if (v_count == V_TOTAL - 1)
                v_count <= 0;
            else
                v_count <= v_count + 1;
        end
    end

    // Sync signals (active low)
    assign hsync = (h_count >= (H_DISPLAY + H_FRONT) && h_count < (H_DISPLAY + H_FRONT + H_SYNC)) ? 0 : 1;
    assign vsync = (v_count >= (V_DISPLAY + V_FRONT) && v_count < (V_DISPLAY + V_FRONT + V_SYNC)) ? 0 : 1;

    // Use testbench-controlled inputs for colors
    always @(posedge clk) begin
        if (h_count < H_DISPLAY && v_count < V_DISPLAY) begin
            red   <= in_red;
            green <= in_green;
            blue  <= in_blue;
        end else begin
            red   <= 4'b0000;
            green <= 4'b0000;
            blue  <= 4'b0000;
        end
    end

endmodule

graphics/tb/tb_int_vga.v
`timescale 1ns / 1ps

module tb_int_vga;

    reg clk = 0;
    reg reset = 1;
    wire hsync, vsync;
    wire [3:0] red, green, blue;

    // Instantiate the VGA module
    int_vga uut (
        .clk(clk),
        .reset(reset),
        .hsync(hsync),
        .vsync(vsync),
        .red(red),
        .green(green),
        .blue(blue)
    );

    // Clock generation (25 MHz for 240p VGA)
    always #20 clk = ~clk;  // 25MHz Clock (40ns period)

    integer file;
    
    initial begin
        // Open file to store VGA output
        file = $fopen("./bin/vga_output.txt", "w");
        if (file == 0) begin
            $display("Error: Could not open file!");
            $finish;
        end

        // Enable waveform dump for debugging
        $dumpfile("./bin/tb_int_vga.vcd");
        $dumpvars(0, tb_int_vga);

        // Reset sequence
        #50 reset = 0;

        // Run simulation for enough time to capture a full frame
        #2000000;

        // Close file and finish simulation
        $fclose(file);
        $finish;
    end

    // Variables to determine line positions
    localparam NUM_LINES = 6;
    localparam LINE_SPACING = 240 / (NUM_LINES + 1);  // Even spacing
    integer i;

    // Capture visible pixel data and draw black lines
    always @(posedge clk) begin
        if (hsync == 1 && vsync == 1) begin  // Only log visible pixels
            // Default color: White
            reg [7:0] pixel_r = 255;
            reg [7:0] pixel_g = 255;
            reg [7:0] pixel_b = 255;

            // Draw 6 black horizontal lines
            for (i = 1; i <= NUM_LINES; i = i + 1) begin
                if (uut.v_count == i * LINE_SPACING) begin
                    pixel_r = 0;
                    pixel_g = 0;
                    pixel_b = 0;
                end
            end

            $fwrite(file, "%d %d %d %d %d\n", uut.h_count, uut.v_count, pixel_r, pixel_g, pixel_b);
        end
    end

endmodule

graphics/bin/tb_int_vga.vcd
$date
	Mon Mar 17 12:22:43 2025
$end
$version
	Icarus Verilog
$end
$timescale
	1ps
$end
$scope module tb_int_vga $end
$var wire 1 ! vsync $end
$var wire 4 " red [3:0] $end
$var wire 1 # hsync $end
$var wire 4 $ green [3:0] $end
$var wire 4 % blue [3:0] $end
$var reg 1 & clk $end
$var reg 1 ' reset $end
$var integer 32 ( file [31:0] $end
$var integer 32 ) i [31:0] $end
$scope module uut $end
$var wire 1 & clk $end
$var wire 4 * in_blue [3:0] $end
$var wire 4 + in_green [3:0] $end
$var wire 4 , in_red [3:0] $end
$var wire 1 ' reset $end
$var wire 1 ! vsync $end
$var wire 1 # hsync $end
$var reg 4 - blue [3:0] $end
$var reg 4 . green [3:0] $end
$var reg 10 / h_count [9:0] $end
$var reg 4 0 red [3:0] $end
$var reg 10 1 v_count [9:0] $end
$upscope $end
$scope begin $unm_blk_4 $end
$var reg 8 2 pixel_b [7:0] $end
$var reg 8 3 pixel_g [7:0] $end
$var reg 8 4 pixel_r [7:0] $end
$upscope $end
$upscope $end
$enddefinitions $end
#0
$dumpvars
b11111111 4
b11111111 3
b11111111 2
b0 1
bx 0
b0 /
bx .
bx -
bz ,
bz +
bz *
bx )
b10000000000000000000000000000011 (
1'
0&
bx %
bx $
1#
bx "
1!
$end
#20000
bz %
bz -
bz $
bz .
bz "
bz 0
b111 )
1&
#40000
0&
#50000
0'
#60000
b1 /
b111 )
1&
#80000
0&
#100000
b10 /
b111 )
1&
#120000
0&
#140000
b11 /
b111 )
1&
#160000
0&
#180000
b100 /
b111 )
1&
#200000
0&
#220000
b101 /
b111 )
1&
#240000
0&
#260000
b110 /
b111 )
1&
#280000
0&
#300000
b111 /
b111 )
1&
#320000
0&
#340000
b1000 /
b111 )
1&
#360000
0&
#380000
b1001 /
b111 )
1&
#400000
0&
#420000
b1010 /
b111 )
1&
#440000
0&
#460000
b1011 /
b111 )
1&
#480000
0&
#500000
b1100 /
b111 )
1&
#520000
0&
#540000
b1101 /
b111 )
1&
#560000
0&
#580000
b1110 /
b111 )
1&
#600000
0&
#620000
b1111 /
b111 )
1&
#640000
0&
#660000
b10000 /
b111 )
1&
#680000
0&
#700000
b10001 /
b111 )
1&
#720000
0&
#740000
b10010 /
b111 )
1&
#760000
0&
#780000
b10011 /
b111 )
1&
#800000
0&
#820000
b10100 /
b111 )
1&
#840000
0&
#860000
b10101 /
b111 )
1&
#880000
0&
#900000
b10110 /
b111 )
1&
#920000
0&
#940000
b10111 /
b111 )
1&
#960000
0&
#980000
b11000 /
b111 )
1&
#1000000
0&
#1020000
b11001 /
b111 )
1&
#1040000
0&
#1060000
b11010 /
b111 )
1&
#1080000
0&
#1100000
b11011 /
b111 )
1&
#1120000
0&
#1140000
b11100 /
b111 )
1&
#1160000
0&
#1180000
b11101 /
b111 )
1&
#1200000
0&
#1220000
b11110 /
b111 )
1&
#1240000
0&
#1260000
b11111 /
b111 )
1&
#1280000
0&
#1300000
b100000 /
b111 )
1&
#1320000
0&
#1340000
b100001 /
b111 )
1&
#1360000
0&
#1380000
b100010 /
b111 )
1&
#1400000
0&
#1420000
b100011 /
b111 )
1&
#1440000
0&
#1460000
b100100 /
b111 )
1&
#1480000
0&
#1500000
b100101 /
b111 )
1&
#1520000
0&
#1540000
b100110 /
b111 )
1&
#1560000
0&
#1580000
b100111 /
b111 )
1&
#1600000
0&
#1620000
b101000 /
b111 )
1&
#1640000
0&
#1660000
b101001 /
b111 )
1&
#1680000
0&
#1700000
b101010 /
b111 )
1&
#1720000
0&
#1740000
b101011 /
b111 )
1&
#1760000
0&
#1780000
b101100 /
b111 )
1&
#1800000
0&
#1820000
b101101 /
b111 )
1&
#1840000
0&
#1860000
b101110 /
b111 )
1&
#1880000
0&
#1900000
b101111 /
b111 )
1&
#1920000
0&
#1940000
b110000 /
b111 )
1&
#1960000
0&
#1980000
b110001 /
b111 )
1&
#2000000
0&
#2020000
b110010 /
b111 )
1&
#2040000
0&
#2060000
b110011 /
b111 )
1&
#2080000
0&
#2100000
b110100 /
b111 )
1&
#2120000
0&
#2140000
b110101 /
b111 )
1&
#2160000
0&
#2180000
b110110 /
b111 )
1&
#2200000
0&
#2220000
b110111 /
b111 )
1&
#2240000
0&
#2260000
b111000 /
b111 )
1&
#2280000
0&
#2300000
b111001 /
b111 )
1&
#2320000
0&
#2340000
b111010 /
b111 )
1&
#2360000
0&
#2380000
b111011 /
b111 )
1&
#2400000
0&
#2420000
b111100 /
b111 )
1&
#2440000
0&
#2460000
b111101 /
b111 )
1&
#2480000
0&
#2500000
b111110 /
b111 )
1&
#2520000
0&
#2540000
b111111 /
b111 )
1&
#2560000
0&
#2580000
b1000000 /
b111 )
1&
#2600000
0&
#2620000
b1000001 /
b111 )
1&
#2640000
0&
#2660000
b1000010 /
b111 )
1&
#2680000
0&
#2700000
b1000011 /
b111 )
1&
#2720000
0&
#2740000
b1000100 /
b111 )
1&
#2760000
0&
#2780000
b1000101 /
b111 )
1&
#2800000
0&
#2820000
b1000110 /
b111 )
1&
#2840000
0&
#2860000
b1000111 /
b111 )
1&
#2880000
0&
#2900000
b1001000 /
b111 )
1&
#2920000
0&
#2940000
b1001001 /
b111 )
1&
#2960000
0&
#2980000
b1001010 /
b111 )
1&
#3000000
0&
#3020000
b1001011 /
b111 )
1&
#3040000
0&
#3060000
b1001100 /
b111 )
1&
#3080000
0&
#3100000
b1001101 /
b111 )
1&
#3120000
0&
#3140000
b1001110 /
b111 )
1&
#3160000
0&
#3180000
b1001111 /
b111 )
1&
#3200000
0&
#3220000
b1010000 /
b111 )
1&
#3240000
0&
#3260000
b1010001 /
b111 )
1&
#3280000
0&
#3300000
b1010010 /
b111 )
1&
#3320000
0&
#3340000
b1010011 /
b111 )
1&
#3360000
0&
#3380000
b1010100 /
b111 )
1&
#3400000
0&
#3420000
b1010101 /
b111 )
1&
#3440000
0&
#3460000
b1010110 /
b111 )
1&
#3480000
0&
#3500000
b1010111 /
b111 )
1&
#3520000
0&
#3540000
b1011000 /
b111 )
1&
#3560000
0&
#3580000
b1011001 /
b111 )
1&
#3600000
0&
#3620000
b1011010 /
b111 )
1&
#3640000
0&
#3660000
b1011011 /
b111 )
1&
#3680000
0&
#3700000
b1011100 /
b111 )
1&
#3720000
0&
#3740000
b1011101 /
b111 )
1&
#3760000
0&
#3780000
b1011110 /
b111 )
1&
#3800000
0&
#3820000
b1011111 /
b111 )
1&
#3840000
0&
#3860000
b1100000 /
b111 )
1&
#3880000
0&
#3900000
b1100001 /
b111 )
1&
#3920000
0&
#3940000
b1100010 /
b111 )
1&
#3960000
0&
#3980000
b1100011 /
b111 )
1&
#4000000
0&
#4020000
b1100100 /
b111 )
1&
#4040000
0&
#4060000
b1100101 /
b111 )
1&
#4080000
0&
#4100000
b1100110 /
b111 )
1&
#4120000
0&
#4140000
b1100111 /
b111 )
1&
#4160000
0&
#4180000
b1101000 /
b111 )
1&
#4200000
0&
#4220000
b1101001 /
b111 )
1&
#4240000
0&
#4260000
b1101010 /
b111 )
1&
#4280000
0&
#4300000
b1101011 /
b111 )
1&
#4320000
0&
#4340000
b1101100 /
b111 )
1&
#4360000
0&
#4380000
b1101101 /
b111 )
1&
#4400000
0&
#4420000
b1101110 /
b111 )
1&
#4440000
0&
#4460000
b1101111 /
b111 )
1&
#4480000
0&
#4500000
b1110000 /
b111 )
1&
#4520000
0&
#4540000
b1110001 /
b111 )
1&
#4560000
0&
#4580000
b1110010 /
b111 )
1&
#4600000
0&
#4620000
b1110011 /
b111 )
1&
#4640000
0&
#4660000
b1110100 /
b111 )
1&
#4680000
0&
#4700000
b1110101 /
b111 )
1&
#4720000
0&
#4740000
b1110110 /
b111 )
1&
#4760000
0&
#4780000
b1110111 /
b111 )
1&
#4800000
0&
#4820000
b1111000 /
b111 )
1&
#4840000
0&
#4860000
b1111001 /
b111 )
1&
#4880000
0&
#4900000
b1111010 /
b111 )
1&
#4920000
0&
#4940000
b1111011 /
b111 )
1&
#4960000
0&
#4980000
b1111100 /
b111 )
1&
#5000000
0&
#5020000
b1111101 /
b111 )
1&
#5040000
0&
#5060000
b1111110 /
b111 )
1&
#5080000
0&
#5100000
b1111111 /
b111 )
1&
#5120000
0&
#5140000
b10000000 /
b111 )
1&
#5160000
0&
#5180000
b10000001 /
b111 )
1&
#5200000
0&
#5220000
b10000010 /
b111 )
1&
#5240000
0&
#5260000
b10000011 /
b111 )
1&
#5280000
0&
#5300000
b10000100 /
b111 )
1&
#5320000
0&
#5340000
b10000101 /
b111 )
1&
#5360000
0&
#5380000
b10000110 /
b111 )
1&
#5400000
0&
#5420000
b10000111 /
b111 )
1&
#5440000
0&
#5460000
b10001000 /
b111 )
1&
#5480000
0&
#5500000
b10001001 /
b111 )
1&
#5520000
0&
#5540000
b10001010 /
b111 )
1&
#5560000
0&
#5580000
b10001011 /
b111 )
1&
#5600000
0&
#5620000
b10001100 /
b111 )
1&
#5640000
0&
#5660000
b10001101 /
b111 )
1&
#5680000
0&
#5700000
b10001110 /
b111 )
1&
#5720000
0&
#5740000
b10001111 /
b111 )
1&
#5760000
0&
#5780000
b10010000 /
b111 )
1&
#5800000
0&
#5820000
b10010001 /
b111 )
1&
#5840000
0&
#5860000
b10010010 /
b111 )
1&
#5880000
0&
#5900000
b10010011 /
b111 )
1&
#5920000
0&
#5940000
b10010100 /
b111 )
1&
#5960000
0&
#5980000
b10010101 /
b111 )
1&
#6000000
0&
#6020000
b10010110 /
b111 )
1&
#6040000
0&
#6060000
b10010111 /
b111 )
1&
#6080000
0&
#6100000
b10011000 /
b111 )
1&
#6120000
0&
#6140000
b10011001 /
b111 )
1&
#6160000
0&
#6180000
b10011010 /
b111 )
1&
#6200000
0&
#6220000
b10011011 /
b111 )
1&
#6240000
0&
#6260000
b10011100 /
b111 )
1&
#6280000
0&
#6300000
b10011101 /
b111 )
1&
#6320000
0&
#6340000
b10011110 /
b111 )
1&
#6360000
0&
#6380000
b10011111 /
b111 )
1&
#6400000
0&
#6420000
b10100000 /
b111 )
1&
#6440000
0&
#6460000
b10100001 /
b111 )
1&
#6480000
0&
#6500000
b10100010 /
b111 )
1&
#6520000
0&
#6540000
b10100011 /
b111 )
1&
#6560000
0&
#6580000
b10100100 /
b111 )
1&
#6600000
0&
#6620000
b10100101 /
b111 )
1&
#6640000
0&
#6660000
b10100110 /
b111 )
1&
#6680000
0&
#6700000
b10100111 /
b111 )
1&
#6720000
0&
#6740000
b10101000 /
b111 )
1&
#6760000
0&
#6780000
b10101001 /
b111 )
1&
#6800000
0&
#6820000
b10101010 /
b111 )
1&
#6840000
0&
#6860000
b10101011 /
b111 )
1&
#6880000
0&
#6900000
b10101100 /
b111 )
1&
#6920000
0&
#6940000
b10101101 /
b111 )
1&
#6960000
0&
#6980000
b10101110 /
b111 )
1&
#7000000
0&
#7020000
b10101111 /
b111 )
1&
#7040000
0&
#7060000
b10110000 /
b111 )
1&
#7080000
0&
#7100000
b10110001 /
b111 )
1&
#7120000
0&
#7140000
b10110010 /
b111 )
1&
#7160000
0&
#7180000
b10110011 /
b111 )
1&
#7200000
0&
#7220000
b10110100 /
b111 )
1&
#7240000
0&
#7260000
b10110101 /
b111 )
1&
#7280000
0&
#7300000
b10110110 /
b111 )
1&
#7320000
0&
#7340000
b10110111 /
b111 )
1&
#7360000
0&
#7380000
b10111000 /
b111 )
1&
#7400000
0&
#7420000
b10111001 /
b111 )
1&
#7440000
0&
#7460000
b10111010 /
b111 )
1&
#7480000
0&
#7500000
b10111011 /
b111 )
1&
#7520000
0&
#7540000
b10111100 /
b111 )
1&
#7560000
0&
#7580000
b10111101 /
b111 )
1&
#7600000
0&
#7620000
b10111110 /
b111 )
1&
#7640000
0&
#7660000
b10111111 /
b111 )
1&
#7680000
0&
#7700000
b11000000 /
b111 )
1&
#7720000
0&
#7740000
b11000001 /
b111 )
1&
#7760000
0&
#7780000
b11000010 /
b111 )
1&
#7800000
0&
#7820000
b11000011 /
b111 )
1&
#7840000
0&
#7860000
b11000100 /
b111 )
1&
#7880000
0&
#7900000
b11000101 /
b111 )
1&
#7920000
0&
#7940000
b11000110 /
b111 )
1&
#7960000
0&
#7980000
b11000111 /
b111 )
1&
#8000000
0&
#8020000
b11001000 /
b111 )
1&
#8040000
0&
#8060000
b11001001 /
b111 )
1&
#8080000
0&
#8100000
b11001010 /
b111 )
1&
#8120000
0&
#8140000
b11001011 /
b111 )
1&
#8160000
0&
#8180000
b11001100 /
b111 )
1&
#8200000
0&
#8220000
b11001101 /
b111 )
1&
#8240000
0&
#8260000
b11001110 /
b111 )
1&
#8280000
0&
#8300000
b11001111 /
b111 )
1&
#8320000
0&
#8340000
b11010000 /
b111 )
1&
#8360000
0&
#8380000
b11010001 /
b111 )
1&
#8400000
0&
#8420000
b11010010 /
b111 )
1&
#8440000
0&
#8460000
b11010011 /
b111 )
1&
#8480000
0&
#8500000
b11010100 /
b111 )
1&
#8520000
0&
#8540000
b11010101 /
b111 )
1&
#8560000
0&
#8580000
b11010110 /
b111 )
1&
#8600000
0&
#8620000
b11010111 /
b111 )
1&
#8640000
0&
#8660000
b11011000 /
b111 )
1&
#8680000
0&
#8700000
b11011001 /
b111 )
1&
#8720000
0&
#8740000
b11011010 /
b111 )
1&
#8760000
0&
#8780000
b11011011 /
b111 )
1&
#8800000
0&
#8820000
b11011100 /
b111 )
1&
#8840000
0&
#8860000
b11011101 /
b111 )
1&
#8880000
0&
#8900000
b11011110 /
b111 )
1&
#8920000
0&
#8940000
b11011111 /
b111 )
1&
#8960000
0&
#8980000
b11100000 /
b111 )
1&
#9000000
0&
#9020000
b11100001 /
b111 )
1&
#9040000
0&
#9060000
b11100010 /
b111 )
1&
#9080000
0&
#9100000
b11100011 /
b111 )
1&
#9120000
0&
#9140000
b11100100 /
b111 )
1&
#9160000
0&
#9180000
b11100101 /
b111 )
1&
#9200000
0&
#9220000
b11100110 /
b111 )
1&
#9240000
0&
#9260000
b11100111 /
b111 )
1&
#9280000
0&
#9300000
b11101000 /
b111 )
1&
#9320000
0&
#9340000
b11101001 /
b111 )
1&
#9360000
0&
#9380000
b11101010 /
b111 )
1&
#9400000
0&
#9420000
b11101011 /
b111 )
1&
#9440000
0&
#9460000
b11101100 /
b111 )
1&
#9480000
0&
#9500000
b11101101 /
b111 )
1&
#9520000
0&
#9540000
b11101110 /
b111 )
1&
#9560000
0&
#9580000
b11101111 /
b111 )
1&
#9600000
0&
#9620000
b11110000 /
b111 )
1&
#9640000
0&
#9660000
b11110001 /
b111 )
1&
#9680000
0&
#9700000
b11110010 /
b111 )
1&
#9720000
0&
#9740000
b11110011 /
b111 )
1&
#9760000
0&
#9780000
b11110100 /
b111 )
1&
#9800000
0&
#9820000
b11110101 /
b111 )
1&
#9840000
0&
#9860000
b11110110 /
b111 )
1&
#9880000
0&
#9900000
b11110111 /
b111 )
1&
#9920000
0&
#9940000
b11111000 /
b111 )
1&
#9960000
0&
#9980000
b11111001 /
b111 )
1&
#10000000
0&
#10020000
b11111010 /
b111 )
1&
#10040000
0&
#10060000
b11111011 /
b111 )
1&
#10080000
0&
#10100000
b11111100 /
b111 )
1&
#10120000
0&
#10140000
b11111101 /
b111 )
1&
#10160000
0&
#10180000
b11111110 /
b111 )
1&
#10200000
0&
#10220000
b11111111 /
b111 )
1&
#10240000
0&
#10260000
b100000000 /
b111 )
1&
#10280000
0&
#10300000
b100000001 /
b111 )
1&
#10320000
0&
#10340000
b100000010 /
b111 )
1&
#10360000
0&
#10380000
b100000011 /
b111 )
1&
#10400000
0&
#10420000
b100000100 /
b111 )
1&
#10440000
0&
#10460000
b100000101 /
b111 )
1&
#10480000
0&
#10500000
b100000110 /
b111 )
1&
#10520000
0&
#10540000
b100000111 /
b111 )
1&
#10560000
0&
#10580000
b100001000 /
b111 )
1&
#10600000
0&
#10620000
b100001001 /
b111 )
1&
#10640000
0&
#10660000
b100001010 /
b111 )
1&
#10680000
0&
#10700000
b100001011 /
b111 )
1&
#10720000
0&
#10740000
b100001100 /
b111 )
1&
#10760000
0&
#10780000
b100001101 /
b111 )
1&
#10800000
0&
#10820000
b100001110 /
b111 )
1&
#10840000
0&
#10860000
b100001111 /
b111 )
1&
#10880000
0&
#10900000
b100010000 /
b111 )
1&
#10920000
0&
#10940000
b100010001 /
b111 )
1&
#10960000
0&
#10980000
b100010010 /
b111 )
1&
#11000000
0&
#11020000
b100010011 /
b111 )
1&
#11040000
0&
#11060000
b100010100 /
b111 )
1&
#11080000
0&
#11100000
b100010101 /
b111 )
1&
#11120000
0&
#11140000
b100010110 /
b111 )
1&
#11160000
0&
#11180000
b100010111 /
b111 )
1&
#11200000
0&
#11220000
b100011000 /
b111 )
1&
#11240000
0&
#11260000
b100011001 /
b111 )
1&
#11280000
0&
#11300000
b100011010 /
b111 )
1&
#11320000
0&
#11340000
b100011011 /
b111 )
1&
#11360000
0&
#11380000
b100011100 /
b111 )
1&
#11400000
0&
#11420000
b100011101 /
b111 )
1&
#11440000
0&
#11460000
b100011110 /
b111 )
1&
#11480000
0&
#11500000
b100011111 /
b111 )
1&
#11520000
0&
#11540000
b100100000 /
b111 )
1&
#11560000
0&
#11580000
b100100001 /
b111 )
1&
#11600000
0&
#11620000
b100100010 /
b111 )
1&
#11640000
0&
#11660000
b100100011 /
b111 )
1&
#11680000
0&
#11700000
b100100100 /
b111 )
1&
#11720000
0&
#11740000
b100100101 /
b111 )
1&
#11760000
0&
#11780000
b100100110 /
b111 )
1&
#11800000
0&
#11820000
b100100111 /
b111 )
1&
#11840000
0&
#11860000
b100101000 /
b111 )
1&
#11880000
0&
#11900000
b100101001 /
b111 )
1&
#11920000
0&
#11940000
b100101010 /
b111 )
1&
#11960000
0&
#11980000
b100101011 /
b111 )
1&
#12000000
0&
#12020000
b100101100 /
b111 )
1&
#12040000
0&
#12060000
b100101101 /
b111 )
1&
#12080000
0&
#12100000
b100101110 /
b111 )
1&
#12120000
0&
#12140000
b100101111 /
b111 )
1&
#12160000
0&
#12180000
b100110000 /
b111 )
1&
#12200000
0&
#12220000
b100110001 /
b111 )
1&
#12240000
0&
#12260000
b100110010 /
b111 )
1&
#12280000
0&
#12300000
b100110011 /
b111 )
1&
#12320000
0&
#12340000
b100110100 /
b111 )
1&
#12360000
0&
#12380000
b100110101 /
b111 )
1&
#12400000
0&
#12420000
b100110110 /
b111 )
1&
#12440000
0&
#12460000
b100110111 /
b111 )
1&
#12480000
0&
#12500000
b100111000 /
b111 )
1&
#12520000
0&
#12540000
b100111001 /
b111 )
1&
#12560000
0&
#12580000
b100111010 /
b111 )
1&
#12600000
0&
#12620000
b100111011 /
b111 )
1&
#12640000
0&
#12660000
b100111100 /
b111 )
1&
#12680000
0&
#12700000
b100111101 /
b111 )
1&
#12720000
0&
#12740000
b100111110 /
b111 )
1&
#12760000
0&
#12780000
b100111111 /
b111 )
1&
#12800000
0&
#12820000
b101000000 /
b111 )
1&
#12840000
0&
#12860000
b0 %
b0 -
b0 $
b0 .
b0 "
b0 0
b101000001 /
b111 )
1&
#12880000
0&
#12900000
b101000010 /
b111 )
1&
#12920000
0&
#12940000
b101000011 /
b111 )
1&
#12960000
0&
#12980000
b101000100 /
b111 )
1&
#13000000
0&
#13020000
b101000101 /
b111 )
1&
#13040000
0&
#13060000
b101000110 /
b111 )
1&
#13080000
0&
#13100000
b101000111 /
b111 )
1&
#13120000
0&
#13140000
0#
b101001000 /
b111 )
1&
#13160000
0&
#13180000
b101001001 /
1&
#13200000
0&
#13220000
b101001010 /
1&
#13240000
0&
#13260000
b101001011 /
1&
#13280000
0&
#13300000
b101001100 /
1&
#13320000
0&
#13340000
b101001101 /
1&
#13360000
0&
#13380000
b101001110 /
1&
#13400000
0&
#13420000
b101001111 /
1&
#13440000
0&
#13460000
b101010000 /
1&
#13480000
0&
#13500000
b101010001 /
1&
#13520000
0&
#13540000
b101010010 /
1&
#13560000
0&
#13580000
b101010011 /
1&
#13600000
0&
#13620000
b101010100 /
1&
#13640000
0&
#13660000
b101010101 /
1&
#13680000
0&
#13700000
b101010110 /
1&
#13720000
0&
#13740000
b101010111 /
1&
#13760000
0&
#13780000
b101011000 /
1&
#13800000
0&
#13820000
b101011001 /
1&
#13840000
0&
#13860000
b101011010 /
1&
#13880000
0&
#13900000
b101011011 /
1&
#13920000
0&
#13940000
b101011100 /
1&
#13960000
0&
#13980000
b101011101 /
1&
#14000000
0&
#14020000
b101011110 /
1&
#14040000
0&
#14060000
b101011111 /
1&
#14080000
0&
#14100000
b101100000 /
1&
#14120000
0&
#14140000
b101100001 /
1&
#14160000
0&
#14180000
b101100010 /
1&
#14200000
0&
#14220000
b101100011 /
1&
#14240000
0&
#14260000
b101100100 /
1&
#14280000
0&
#14300000
b101100101 /
1&
#14320000
0&
#14340000
b101100110 /
1&
#14360000
0&
#14380000
b101100111 /
1&
#14400000
0&
#14420000
b101101000 /
1&
#14440000
0&
#14460000
b101101001 /
1&
#14480000
0&
#14500000
b101101010 /
1&
#14520000
0&
#14540000
b101101011 /
1&
#14560000
0&
#14580000
b101101100 /
1&
#14600000
0&
#14620000
b101101101 /
1&
#14640000
0&
#14660000
b101101110 /
1&
#14680000
0&
#14700000
b101101111 /
1&
#14720000
0&
#14740000
b101110000 /
1&
#14760000
0&
#14780000
b101110001 /
1&
#14800000
0&
#14820000
b101110010 /
1&
#14840000
0&
#14860000
b101110011 /
1&
#14880000
0&
#14900000
b101110100 /
1&
#14920000
0&
#14940000
b101110101 /
1&
#14960000
0&
#14980000
b101110110 /
1&
#15000000
0&
#15020000
b101110111 /
1&
#15040000
0&
#15060000
1#
b101111000 /
1&
#15080000
0&
#15100000
b101111001 /
b111 )
1&
#15120000
0&
#15140000
b101111010 /
b111 )
1&
#15160000
0&
#15180000
b101111011 /
b111 )
1&
#15200000
0&
#15220000
b101111100 /
b111 )
1&
#15240000
0&
#15260000
b101111101 /
b111 )
1&
#15280000
0&
#15300000
b101111110 /
b111 )
1&
#15320000
0&
#15340000
b101111111 /
b111 )
1&
#15360000
0&
#15380000
b110000000 /
b111 )
1&
#15400000
0&
#15420000
b110000001 /
b111 )
1&
#15440000
0&
#15460000
b110000010 /
b111 )
1&
#15480000
0&
#15500000
b110000011 /
b111 )
1&
#15520000
0&
#15540000
b110000100 /
b111 )
1&
#15560000
0&
#15580000
b110000101 /
b111 )
1&
#15600000
0&
#15620000
b110000110 /
b111 )
1&
#15640000
0&
#15660000
b110000111 /
b111 )
1&
#15680000
0&
#15700000
b110001000 /
b111 )
1&
#15720000
0&
#15740000
b110001001 /
b111 )
1&
#15760000
0&
#15780000
b110001010 /
b111 )
1&
#15800000
0&
#15820000
b110001011 /
b111 )
1&
#15840000
0&
#15860000
b110001100 /
b111 )
1&
#15880000
0&
#15900000
b110001101 /
b111 )
1&
#15920000
0&
#15940000
b110001110 /
b111 )
1&
#15960000
0&
#15980000
b110001111 /
b111 )
1&
#16000000
0&
#16020000
b0 /
b1 1
b111 )
1&
#16040000
0&
#16060000
bz %
bz -
bz $
bz .
bz "
bz 0
b1 /
b111 )
1&
#16080000
0&
#16100000
b10 /
b111 )
1&
#16120000
0&
#16140000
b11 /
b111 )
1&
#16160000
0&
#16180000
b100 /
b111 )
1&
#16200000
0&
#16220000
b101 /
b111 )
1&
#16240000
0&
#16260000
b110 /
b111 )
1&
#16280000
0&
#16300000
b111 /
b111 )
1&
#16320000
0&
#16340000
b1000 /
b111 )
1&
#16360000
0&
#16380000
b1001 /
b111 )
1&
#16400000
0&
#16420000
b1010 /
b111 )
1&
#16440000
0&
#16460000
b1011 /
b111 )
1&
#16480000
0&
#16500000
b1100 /
b111 )
1&
#16520000
0&
#16540000
b1101 /
b111 )
1&
#16560000
0&
#16580000
b1110 /
b111 )
1&
#16600000
0&
#16620000
b1111 /
b111 )
1&
#16640000
0&
#16660000
b10000 /
b111 )
1&
#16680000
0&
#16700000
b10001 /
b111 )
1&
#16720000
0&
#16740000
b10010 /
b111 )
1&
#16760000
0&
#16780000
b10011 /
b111 )
1&
#16800000
0&
#16820000
b10100 /
b111 )
1&
#16840000
0&
#16860000
b10101 /
b111 )
1&
#16880000
0&
#16900000
b10110 /
b111 )
1&
#16920000
0&
#16940000
b10111 /
b111 )
1&
#16960000
0&
#16980000
b11000 /
b111 )
1&
#17000000
0&
#17020000
b11001 /
b111 )
1&
#17040000
0&
#17060000
b11010 /
b111 )
1&
#17080000
0&
#17100000
b11011 /
b111 )
1&
#17120000
0&
#17140000
b11100 /
b111 )
1&
#17160000
0&
#17180000
b11101 /
b111 )
1&
#17200000
0&
#17220000
b11110 /
b111 )
1&
#17240000
0&
#17260000
b11111 /
b111 )
1&
#17280000
0&
#17300000
b100000 /
b111 )
1&
#17320000
0&
#17340000
b100001 /
b111 )
1&
#17360000
0&
#17380000
b100010 /
b111 )
1&
#17400000
0&
#17420000
b100011 /
b111 )
1&
#17440000
0&
#17460000
b100100 /
b111 )
1&
#17480000
0&
#17500000
b100101 /
b111 )
1&
#17520000
0&
#17540000
b100110 /
b111 )
1&
#17560000
0&
#17580000
b100111 /
b111 )
1&
#17600000
0&
#17620000
b101000 /
b111 )
1&
#17640000
0&
#17660000
b101001 /
b111 )
1&
#17680000
0&
#17700000
b101010 /
b111 )
1&
#17720000
0&
#17740000
b101011 /
b111 )
1&
#17760000
0&
#17780000
b101100 /
b111 )
1&
#17800000
0&
#17820000
b101101 /
b111 )
1&
#17840000
0&
#17860000
b101110 /
b111 )
1&
#17880000
0&
#17900000
b101111 /
b111 )
1&
#17920000
0&
#17940000
b110000 /
b111 )
1&
#17960000
0&
#17980000
b110001 /
b111 )
1&
#18000000
0&
#18020000
b110010 /
b111 )
1&
#18040000
0&
#18060000
b110011 /
b111 )
1&
#18080000
0&
#18100000
b110100 /
b111 )
1&
#18120000
0&
#18140000
b110101 /
b111 )
1&
#18160000
0&
